procdrive/__init__.py
procdrive-1.0.0.dist-info/LICENSE
procdrive-1.0.0.dist-info/METADATA
procdrive-1.0.0.dist-info/WHEEL
procdrive-1.0.0.dist-info/top_level.txt
procdrive-1.0.0.dist-info/RECORD
