Metadata-Version: 2.1
Name: procdrive
Version: 1.0.0
Summary: Procedural wrappe for controlling a single Anki Overdrive vehicle
Author: Pascal Rombach
Project-URL: Homepage, https://github.com/PascalRombach/procdrive
Keywords: Anki Overdrive,Anki,Procedural
Classifier: Programming Language :: Python :: 3
Classifier: Programming Language :: Python :: Implementation :: CPython
Classifier: Operating System :: OS Independent
Classifier: Topic :: Education
Classifier: Topic :: Software Development :: Libraries :: Python Modules
Requires-Python: >=3.10
License-File: LICENSE
Requires-Dist: py-easydrive
